aioswitcher/__init__.py
aioswitcher/api/__init__.py
aioswitcher/api/messages.py
aioswitcher/api/packets.py
aioswitcher/api/remotes.py
aioswitcher/bridge.py
aioswitcher/device/__init__.py
aioswitcher/device/tools.py
aioswitcher/py.typed
aioswitcher/resources/irset_db.json
aioswitcher/schedule/__init__.py
aioswitcher/schedule/parser.py
aioswitcher/schedule/tools.py
aioswitcher-6.0.3.dist-info/LICENSE
aioswitcher-6.0.3.dist-info/METADATA
aioswitcher-6.0.3.dist-info/WHEEL
aioswitcher-6.0.3.dist-info/entry_points.txt
aioswitcher-6.0.3.dist-info/RECORD
