Metadata-Version: 2.3
Name: aioswitcher
Version: 6.0.3
Summary: PyPi module integrating with various Switcher devices
License: Apache-2.0
Keywords: home-automation,smarthome,switcher
Author: Tomer Figenblat
Author-email: tomer@tomfi.info
Maintainer: Shay Levy
Requires-Python: >=3.12.0,<4.0
Classifier: Intended Audience :: Developers
Classifier: Operating System :: OS Independent
Classifier: Topic :: Home Automation
Classifier: Topic :: Software Development :: Libraries :: Python Modules
Classifier: Typing :: Typed
Requires-Dist: aiohttp (>=3.10.3,<4.0.0)
Requires-Dist: pycryptodome (>=3.18.0,<4.0.0)
Project-URL: Documentation, https://aioswitcher.figenblat.com
Project-URL: Homepage, https://pypi.org/project/aioswitcher/
Project-URL: Repository, https://github.com/tomerfi/aioswitcher
